abilian/__init__.py
abilian/app.py
abilian/backports.py
abilian/cli/__init__.py
abilian/cli/base.py
abilian/cli/config.py
abilian/cli/indexing.py
abilian/config.py
abilian/core/__init__.py
abilian/core/celery.py
abilian/core/default_logging.yml
abilian/core/entities.py
abilian/core/extensions/__init__.py
abilian/core/extensions/csrf.py
abilian/core/extensions/jinjaext.py
abilian/core/extensions/login.py
abilian/core/extensions/redis.py
abilian/core/extensions/upstream_info.py
abilian/core/logging.py
abilian/core/models/__init__.py
abilian/core/models/attachment.py
abilian/core/models/base.py
abilian/core/models/blob.py
abilian/core/models/comment.py
abilian/core/models/owned.py
abilian/core/models/subjects.py
abilian/core/models/tag.py
abilian/core/models/tests/__init__.py
abilian/core/models/tests/test_blob.py
abilian/core/models/tests/test_comment.py
abilian/core/models/tests/test_subject.py
abilian/core/signals.py
abilian/core/singleton.py
abilian/core/sqlalchemy.py
abilian/core/tests/__init__.py
abilian/core/tests/dummy.py
abilian/core/tests/test_entities.py
abilian/core/tests/test_permissions.py
abilian/core/tests/test_sa_extensions.py
abilian/core/tests/test_singleton.py
abilian/core/tests/test_utils.py
abilian/core/util.py
abilian/i18n.py
abilian/sbe/__init__.py
abilian/sbe/app.py
abilian/sbe/apps/__init__.py
abilian/sbe/apps/calendar/__init__.py
abilian/sbe/apps/calendar/actions.py
abilian/sbe/apps/calendar/forms.py
abilian/sbe/apps/calendar/models.py
abilian/sbe/apps/calendar/templates/calendar/_base.html
abilian/sbe/apps/calendar/templates/calendar/archives.html
abilian/sbe/apps/calendar/templates/calendar/event.html
abilian/sbe/apps/calendar/templates/calendar/index.html
abilian/sbe/apps/calendar/tests/__init__.py
abilian/sbe/apps/calendar/tests/tests.py
abilian/sbe/apps/calendar/views.py
abilian/sbe/apps/communities/__init__.py
abilian/sbe/apps/communities/actions.py
abilian/sbe/apps/communities/blueprint.py
abilian/sbe/apps/communities/common.py
abilian_sbe_next-1.0.4.dist-info/METADATA
abilian_sbe_next-1.0.4.dist-info/WHEEL
abilian_sbe_next-1.0.4.dist-info/RECORD
