Metadata-Version: 2.1
Name: abilian-sbe-next
Version: 1.0.4
Summary: 
Author: Abilian SAS
Author-email: contact@abilian.com
Requires-Python: >=3.9,<3.12
Classifier: Programming Language :: Python :: 3
Classifier: Programming Language :: Python :: 3.9
Classifier: Programming Language :: Python :: 3.10
Classifier: Programming Language :: Python :: 3.11
Requires-Dist: Babel
Requires-Dist: Flask (>=2.1,<2.2)
Requires-Dist: Flask-WTF (>=0.12,<0.13)
Requires-Dist: MarkupSafe (>=2.1.1)
Requires-Dist: PyYAML
Requires-Dist: WTForms-Alchemy (>=0.17.0)
Requires-Dist: Whoosh (>=2.7.4,<3.0.0)
Requires-Dist: bcrypt
Requires-Dist: bleach[css] (>=5.0.1,<6.0.0)
Requires-Dist: blinker
Requires-Dist: celery (>=5.2.7,<5.3.0)
Requires-Dist: chardet
Requires-Dist: clamd
Requires-Dist: click
Requires-Dist: closure (==20161201)
Requires-Dist: cssmin
Requires-Dist: defusedxml (>=0.7.1,<0.8.0)
Requires-Dist: deprecated
Requires-Dist: devtools
Requires-Dist: flask-assets (>=0.12)
Requires-Dist: flask-babel (>=1.0.0,<1.1.0)
Requires-Dist: flask-login (>=0.6.2)
Requires-Dist: flask-mail (>=0.9.1)
Requires-Dist: flask-migrate (>=3.1.0)
Requires-Dist: flask-sqlalchemy (>=2.1,<2.2)
Requires-Dist: flask-tailwind (>=0.2.2,<0.3.0)
Requires-Dist: flask-talisman (>=1.0.0)
Requires-Dist: gunicorn
Requires-Dist: html2text (>=2020.1.16,<2021.0.0)
Requires-Dist: hyperlink
Requires-Dist: icecream
Requires-Dist: importlib-resources (>=5.10.0,<6.0.0)
Requires-Dist: itsdangerous
Requires-Dist: jinja2 (>=3.0,<3.1)
Requires-Dist: jsmin
Requires-Dist: langid (>=1.1.6)
Requires-Dist: lxml
Requires-Dist: markdown (>=3,<4)
Requires-Dist: numpy (>=1.26.0,<2.0.0)
Requires-Dist: openpyxl
Requires-Dist: pandas (>=1.5.0)
Requires-Dist: pillow
Requires-Dist: psycopg2 (>=2.9.9,<3.0.0)
Requires-Dist: pygeoip
Requires-Dist: pytest
Requires-Dist: python-dateutil (>=2.8.2,<3.0.0)
Requires-Dist: python-dotenv (>=1.0.0,<2.0.0)
Requires-Dist: python-magic
Requires-Dist: pytz
Requires-Dist: redis (>=3.5.3,<3.6.0)
Requires-Dist: requests
Requires-Dist: sentry-sdk[flask]
Requires-Dist: sqlalchemy (>=1.3.24,<1.4.0)
Requires-Dist: toml
Requires-Dist: toolz
Requires-Dist: tqdm
Requires-Dist: validate_email
Requires-Dist: webassets (<2)
Requires-Dist: werkzeug (>=2.0,<2.1)
Requires-Dist: wtforms (<2.2)
Requires-Dist: wtforms-sqlalchemy
Requires-Dist: xlwt
